{
  "type": "GROUP",
"name": "Global Information",
"path": "",
"pathFormatted": "group_missing-name-b06d1",
"stats": {
    "name": "Global Information",
    "numberOfRequests": {
        "total": 2,
        "ok": 2,
        "ko": 0
    },
    "minResponseTime": {
        "total": 59,
        "ok": 59,
        "ko": 0
    },
    "maxResponseTime": {
        "total": 203,
        "ok": 203,
        "ko": 0
    },
    "meanResponseTime": {
        "total": 131,
        "ok": 131,
        "ko": 0
    },
    "standardDeviation": {
        "total": 72,
        "ok": 72,
        "ko": 0
    },
    "percentiles1": {
        "total": 131,
        "ok": 131,
        "ko": 0
    },
    "percentiles2": {
        "total": 167,
        "ok": 167,
        "ko": 0
    },
    "percentiles3": {
        "total": 196,
        "ok": 196,
        "ko": 0
    },
    "percentiles4": {
        "total": 202,
        "ok": 202,
        "ko": 0
    },
    "group1": {
        "name": "t < 800 ms",
        "count": 2,
        "percentage": 100
    },
    "group2": {
        "name": "800 ms < t < 1200 ms",
        "count": 0,
        "percentage": 0
    },
    "group3": {
        "name": "t > 1200 ms",
        "count": 0,
        "percentage": 0
    },
    "group4": {
        "name": "failed",
        "count": 0,
        "percentage": 0
    },
    "meanNumberOfRequestsPerSecond": {
        "total": 2.0,
        "ok": 2.0,
        "ko": 0
    }
},
"contents": {
"req_token-generate-a225a": {
        "type": "REQUEST",
        "name": "token generate",
"path": "token generate",
"pathFormatted": "req_token-generate-a225a",
"stats": {
    "name": "token generate",
    "numberOfRequests": {
        "total": 1,
        "ok": 1,
        "ko": 0
    },
    "minResponseTime": {
        "total": 203,
        "ok": 203,
        "ko": 0
    },
    "maxResponseTime": {
        "total": 203,
        "ok": 203,
        "ko": 0
    },
    "meanResponseTime": {
        "total": 203,
        "ok": 203,
        "ko": 0
    },
    "standardDeviation": {
        "total": 0,
        "ok": 0,
        "ko": 0
    },
    "percentiles1": {
        "total": 203,
        "ok": 203,
        "ko": 0
    },
    "percentiles2": {
        "total": 203,
        "ok": 203,
        "ko": 0
    },
    "percentiles3": {
        "total": 203,
        "ok": 203,
        "ko": 0
    },
    "percentiles4": {
        "total": 203,
        "ok": 203,
        "ko": 0
    },
    "group1": {
        "name": "t < 800 ms",
        "count": 1,
        "percentage": 100
    },
    "group2": {
        "name": "800 ms < t < 1200 ms",
        "count": 0,
        "percentage": 0
    },
    "group3": {
        "name": "t > 1200 ms",
        "count": 0,
        "percentage": 0
    },
    "group4": {
        "name": "failed",
        "count": 0,
        "percentage": 0
    },
    "meanNumberOfRequestsPerSecond": {
        "total": 1.0,
        "ok": 1.0,
        "ko": 0
    }
}
    },"req_login-ol-62437": {
        "type": "REQUEST",
        "name": "login ol",
"path": "login ol",
"pathFormatted": "req_login-ol-62437",
"stats": {
    "name": "login ol",
    "numberOfRequests": {
        "total": 1,
        "ok": 1,
        "ko": 0
    },
    "minResponseTime": {
        "total": 59,
        "ok": 59,
        "ko": 0
    },
    "maxResponseTime": {
        "total": 59,
        "ok": 59,
        "ko": 0
    },
    "meanResponseTime": {
        "total": 59,
        "ok": 59,
        "ko": 0
    },
    "standardDeviation": {
        "total": 0,
        "ok": 0,
        "ko": 0
    },
    "percentiles1": {
        "total": 59,
        "ok": 59,
        "ko": 0
    },
    "percentiles2": {
        "total": 59,
        "ok": 59,
        "ko": 0
    },
    "percentiles3": {
        "total": 59,
        "ok": 59,
        "ko": 0
    },
    "percentiles4": {
        "total": 59,
        "ok": 59,
        "ko": 0
    },
    "group1": {
        "name": "t < 800 ms",
        "count": 1,
        "percentage": 100
    },
    "group2": {
        "name": "800 ms < t < 1200 ms",
        "count": 0,
        "percentage": 0
    },
    "group3": {
        "name": "t > 1200 ms",
        "count": 0,
        "percentage": 0
    },
    "group4": {
        "name": "failed",
        "count": 0,
        "percentage": 0
    },
    "meanNumberOfRequestsPerSecond": {
        "total": 1.0,
        "ok": 1.0,
        "ko": 0
    }
}
    }
}

}